TTT/__init__.py
torch-tensor-type/__init__.py
torch_tensor_type-0.1.2.dist-info/LICENSE
torch_tensor_type-0.1.2.dist-info/METADATA
torch_tensor_type-0.1.2.dist-info/WHEEL
torch_tensor_type-0.1.2.dist-info/top_level.txt
torch_tensor_type-0.1.2.dist-info/RECORD
