Metadata-Version: 2.1
Name: torch-tensor-type
Version: 0.1.2
Summary: Practical Pipelining for pyTorch
Home-page: https://github.com/HiiGHoVuTi/TorchTensorTypes
Author: Maxime
Author-email: himyundevacc@gmail.com
License: UNKNOWN
Platform: UNKNOWN
Classifier: Programming Language :: Python :: 3
Classifier: License :: OSI Approved :: MIT License
Classifier: Operating System :: OS Independent
Requires-Python: >=3.6
